<PAMDataset>
  <Metadata domain="IMAGE_STRUCTURE">
    <MDI key="COMPRESSION">JPEG</MDI>
    <MDI key="INTERLEAVE">PIXEL</MDI>
    <MDI key="SOURCE_COLOR_SPACE">YCbCr</MDI>
  </Metadata>
  <Metadata domain="xml:ESRI" format="xml">
    <GeodataXform xsi:type="typens:SplineXform" xmlns:xsi="http://www.w3.org/2001/XMLSchema-instance" xmlns:xs="http://www.w3.org/2001/XMLSchema" xmlns:typens="http://www.esri.com/schemas/ArcGIS/3.0.0">
      <SpatialReference xsi:type="typens:ProjectedCoordinateSystem">
        <WKT>PROJCS["WGS_1984_Web_Mercator_Auxiliary_Sphere",GEOGCS["GCS_WGS_1984",DATUM["D_WGS_1984",SPHEROID["WGS_1984",6378137.0,298.257223563]],PRIMEM["Greenwich",0.0],UNIT["Degree",0.0174532925199433]],PROJECTION["Mercator_Auxiliary_Sphere"],PARAMETER["False_Easting",0.0],PARAMETER["False_Northing",0.0],PARAMETER["Central_Meridian",0.0],PARAMETER["Standard_Parallel_1",0.0],PARAMETER["Auxiliary_Sphere_Type",0.0],UNIT["Meter",1.0],AUTHORITY["EPSG",3857]]</WKT>
        <XOrigin>-20037700</XOrigin>
        <YOrigin>-30241100</YOrigin>
        <XYScale>148923141.92838538</XYScale>
        <ZOrigin>-100000</ZOrigin>
        <ZScale>10000</ZScale>
        <MOrigin>-100000</MOrigin>
        <MScale>10000</MScale>
        <XYTolerance>0.001</XYTolerance>
        <ZTolerance>0.001</ZTolerance>
        <MTolerance>0.001</MTolerance>
        <HighPrecision>true</HighPrecision>
        <WKID>102100</WKID>
        <LatestWKID>3857</LatestWKID>
      </SpatialReference>
      <SourceGCPs xsi:type="typens:ArrayOfDouble">
        <Double>2338.0600815558623</Double>
        <Double>-1422.061430101511</Double>
        <Double>2435.1009364319571</Double>
        <Double>-1901.6554855367185</Double>
        <Double>2587.6339794129162</Double>
        <Double>-1948.9704509328585</Double>
        <Double>2514.2077355622314</Double>
        <Double>-2084.9804641269147</Double>
        <Double>2281.495503235732</Double>
        <Double>-1893.4099585216027</Double>
        <Double>2085.9583069113723</Double>
        <Double>-2149.6251903322991</Double>
        <Double>2143.136821786713</Double>
        <Double>-2438.2879284508526</Double>
        <Double>2151.6969709500845</Double>
        <Double>-2545.6125219475944</Double>
        <Double>1724.3097832025771</Double>
        <Double>-2760.1275635424536</Double>
        <Double>2090.8977324761272</Double>
        <Double>-1743.1428390294313</Double>
        <Double>1871.6253092606428</Double>
        <Double>-2575.7165787262011</Double>
        <Double>2325.6073602446413</Double>
        <Double>-2112.4631585398397</Double>
        <Double>2112.1198397338503</Double>
        <Double>-1939.3480636221282</Double>
        <Double>2182.2250592928585</Double>
        <Double>-2036.0796342612791</Double>
        <Double>2142.6442022044448</Double>
        <Double>-1804.8580893996686</Double>
        <Double>2220.4834279124034</Double>
        <Double>-1717.3707880761142</Double>
      </SourceGCPs>
      <TargetGCPs xsi:type="typens:ArrayOfDouble">
        <Double>950452.13990088354</Double>
        <Double>6004842.2468610555</Double>
        <Double>950912.69107992516</Double>
        <Double>6002971.0490032844</Double>
        <Double>951432.95226141182</Double>
        <Double>6002813.4140308937</Double>
        <Double>951152.32254699839</Double>
        <Double>6002213.5680163354</Double>
        <Double>950485.82697526691</Double>
        <Double>6003076.5043881554</Double>
        <Double>949725.03981949238</Double>
        <Double>6001879.3380264686</Double>
        <Double>949799.12606409739</Double>
        <Double>6000455.9841149645</Double>
        <Double>949868.72223327192</Double>
        <Double>6000209.0299662808</Double>
        <Double>948026.80910272</Double>
        <Double>5999207.3222006867</Double>
        <Double>949891.17261042551</Double>
        <Double>6003435.14916318</Double>
        <Double>948957.23692085769</Double>
        <Double>5999887.9895729944</Double>
        <Double>950713.83861822891</Double>
        <Double>6002111.8397448668</Double>
        <Double>949817.08636582142</Double>
        <Double>6002820.0088291904</Double>
        <Double>950142.61683454085</Double>
        <Double>6002521.4188130554</Double>
        <Double>949960.76877960085</Double>
        <Double>6003289.2217116905</Double>
        <Double>950209.96796599997</Double>
        <Double>6003668.6330855777</Double>
      </TargetGCPs>
    </GeodataXform>
  </Metadata>
  <PAMRasterBand band="1">
    <Histograms>
      <HistItem>
        <HistMin>-0.5</HistMin>
        <HistMax>255.5</HistMax>
        <BucketCount>256</BucketCount>
        <IncludeOutOfRange>1</IncludeOutOfRange>
        <Approximate>0</Approximate>
        <HistCounts>1655394|26654|17934|14197|10275|7398|6879|6221|5983|5561|5446|5254|5144|5066|4898|4814|4869|5022|4903|4947|5086|5055|5192|5475|5307|5465|5534|5807|5892|5977|6159|6281|6551|6844|7132|7222|7532|8078|8069|8574|8976|9296|9320|9803|9614|9765|9639|9484|9149|8953|8913|8673|8462|8287|8225|8321|7981|7976|7535|7241|6719|6239|5579|5140|4528|3943|3457|3100|2813|2352|2233|1946|1761|1659|1515|1466|1579|1592|1629|1801|2033|2297|2619|2868|3258|3545|3909|4301|4609|4866|5239|5389|5444|5822|5960|5990|6399|6870|7968|9519|12863|18795|27243|39991|55919|75232|95146|111810|120495|119256|107730|95539|83362|71644|60095|49893|40943|33745|28623|24930|22786|21374|20801|20333|20198|20447|21171|21794|22172|22785|23498|24352|24932|25764|26792|27384|28515|29210|30001|30624|31181|32240|33527|34065|35191|36198|37900|38965|40816|42375|44102|45979|47952|49820|51902|53784|55781|56857|58078|59551|60417|61466|61862|62401|62766|63363|63212|63037|63599|63477|63162|63063|62885|63009|63090|63300|62295|62313|62132|61863|61946|62256|62225|63280|64540|65856|66559|69047|71524|74333|77415|80741|85491|89401|94822|100763|107439|114692|122814|130641|138887|149277|158866|168952|180226|190865|201645|211474|220811|226684|231893|236147|240800|246550|254658|264158|273839|281371|285274|284693|287531|297099|321449|370293|445315|563666|714704|887940|1052007|1160966|1176866|1068327|858013|595791|352659|182060|93551|55153|38882|27366|16340|9903|9116|11018|13051|13691|12878|11094|6926|3397|1512|1157|2777|8080|19654|58648</HistCounts>
      </HistItem>
    </Histograms>
    <Metadata domain="IMAGE_STRUCTURE">
      <MDI key="COMPRESSION">JPEG</MDI>
    </Metadata>
    <Metadata>
      <MDI key="STATISTICS_COVARIANCES">4500.722026228153,3880.851717342321,3369.885872548593</MDI>
      <MDI key="STATISTICS_MAXIMUM">255</MDI>
      <MDI key="STATISTICS_MEAN">186.26099662864</MDI>
      <MDI key="STATISTICS_MEDIAN">217.000000</MDI>
      <MDI key="STATISTICS_MINIMUM">0</MDI>
      <MDI key="STATISTICS_SKIPFACTORX">1</MDI>
      <MDI key="STATISTICS_SKIPFACTORY">1</MDI>
      <MDI key="STATISTICS_STDDEV">67.087420774898</MDI>
    </Metadata>
  </PAMRasterBand>
  <PAMRasterBand band="2">
    <Histograms>
      <HistItem>
        <HistMin>-0.5</HistMin>
        <HistMax>250.5</HistMax>
        <BucketCount>251</BucketCount>
        <IncludeOutOfRange>1</IncludeOutOfRange>
        <Approximate>0</Approximate>
        <HistCounts>1591148|6091|2880|2306|2242|2283|2261|2339|2434|2407|2537|2520|2421|2353|2310|2287|2191|2239|2141|2240|2247|2226|2248|2261|2160|2205|2245|2490|2703|2935|3271|3626|4168|4640|5319|5832|6718|7937|9097|10336|11833|13298|14691|15686|16977|17984|18936|19803|20540|21592|22049|21918|22637|22753|22730|22014|21089|19637|17663|15351|13000|10731|8809|6915|5719|4658|3870|3447|3242|3221|3464|3743|3961|4572|5125|5431|5965|6557|6814|7151|7442|7684|7676|7910|8210|8440|8797|8908|9254|9539|9889|10114|10953|11447|12271|12744|13396|14505|15710|17468|20400|24940|32294|43036|58010|75902|95393|114728|129686|135289|129668|119422|107109|96574|86157|76526|67305|58758|52478|47769|44794|41974|40524|39059|38343|38365|37908|37668|38038|39117|40138|42121|44673|47354|49731|51663|52202|52143|51122|50707|49680|50677|51305|52788|53080|53728|54524|55842|56836|59565|62096|65915|70671|73472|74540|73217|70597|67110|64282|62482|62455|62614|62778|64088|64851|66661|67067|68627|70491|71959|73501|75260|76994|79191|80674|82397|83779|84633|84998|85518|86334|87821|89003|90845|93676|96554|100789|106008|111929|120070|129703|140639|155578|172859|194845|220620|252540|287133|324602|363571|400472|431722|459480|479481|502623|533348|575999|644608|747251|866431|969281|1031971|1038255|969715|820784|612538|392533|207907|91459|38604|25952|26606|24326|16264|12297|15291|22327|29730|31063|27524|23639|22460|23686|26488|29018|27509|18679|8989|2923|868|336|214|146|125|108|64|49|25|8|4|1</HistCounts>
      </HistItem>
    </Histograms>
    <Metadata domain="IMAGE_STRUCTURE">
      <MDI key="COMPRESSION">JPEG</MDI>
    </Metadata>
    <Metadata>
      <MDI key="STATISTICS_COVARIANCES">3880.851717342321,3731.591174321776,3259.294451287915</MDI>
      <MDI key="STATISTICS_MAXIMUM">250</MDI>
      <MDI key="STATISTICS_MEAN">171.79921100574</MDI>
      <MDI key="STATISTICS_MEDIAN">201.000000</MDI>
      <MDI key="STATISTICS_MINIMUM">0</MDI>
      <MDI key="STATISTICS_SKIPFACTORX">1</MDI>
      <MDI key="STATISTICS_SKIPFACTORY">1</MDI>
      <MDI key="STATISTICS_STDDEV">61.086751217607</MDI>
    </Metadata>
  </PAMRasterBand>
  <PAMRasterBand band="3">
    <Histograms>
      <HistItem>
        <HistMin>-0.5</HistMin>
        <HistMax>249.5</HistMax>
        <BucketCount>250</BucketCount>
        <IncludeOutOfRange>1</IncludeOutOfRange>
        <Approximate>0</Approximate>
        <HistCounts>1587719|2703|5753|3424|4685|5779|6857|8651|10018|12337|11866|9436|8070|7184|6361|5840|5351|5127|4369|3876|3624|3331|3117|2927|2897|2866|2814|2712|2722|2780|2902|3110|3279|3580|3811|4452|5081|5752|6440|7414|8635|9614|10903|12186|13349|14251|14877|15746|15771|15829|15519|15430|14574|13758|12575|11545|10547|9533|8604|7753|7006|6466|6367|6045|6177|6199|6605|6805|7198|7532|7737|8112|8138|8358|9047|9477|10251|11452|12986|14945|17079|19328|21008|22486|22936|22994|22923|22493|22682|23448|24010|24857|25540|26643|27484|28528|29685|32017|35753|42024|51239|63806|80257|99254|118513|134575|144948|145348|136262|124419|112698|100581|89286|79560|70207|63879|59416|57944|56931|57215|58148|58374|58439|58276|57200|56577|56254|55785|55461|55206|54929|55112|54633|54329|54434|54206|54615|55375|55982|56382|56896|58087|59583|60525|62323|63763|65584|67227|68994|70636|71866|73497|75780|76934|78869|80302|82569|84462|86916|89915|92341|95400|97761|102102|107186|112655|119223|127631|138468|150056|163101|177976|195860|217388|241259|269606|300316|332113|363131|393624|415697|431009|434682|429471|420498|418607|428613|455508|505139|567259|644476|722165|788824|825258|826706|780278|691565|574999|445340|322559|221565|140635|81987|45723|28782|22976|21423|21111|19564|15858|11649|7455|4592|3106|2275|2234|2257|2599|3249|4404|6124|8649|11657|14695|17082|19418|22239|26048|28522|31284|34293|34372|28592|16847|7756|3617|1932|1157|633|377|187|88|45|18|6|2|1|1|1|1</HistCounts>
      </HistItem>
    </Histograms>
    <Metadata domain="IMAGE_STRUCTURE">
      <MDI key="COMPRESSION">JPEG</MDI>
    </Metadata>
    <Metadata>
      <MDI key="STATISTICS_COVARIANCES">3369.885872548593,3259.294451287915,3105.537246080701</MDI>
      <MDI key="STATISTICS_MAXIMUM">249</MDI>
      <MDI key="STATISTICS_MEAN">156.90560316454</MDI>
      <MDI key="STATISTICS_MEDIAN">181.000000</MDI>
      <MDI key="STATISTICS_MINIMUM">0</MDI>
      <MDI key="STATISTICS_SKIPFACTORX">1</MDI>
      <MDI key="STATISTICS_SKIPFACTORY">1</MDI>
      <MDI key="STATISTICS_STDDEV">55.727347380624</MDI>
    </Metadata>
  </PAMRasterBand>
</PAMDataset>
